{"id":229527,"name":"miserably","type":"adverb","us_sound":"ˈmɪz.ɚ.ə.bli","us_link":"../audio/m/miserably.mp3","uk_sound":"ˈmɪz.ər.ə.bli","uk_link":"../audio/m/ukmisch019.mp3","content":"miserably adverb\n(UNHAPPILY)\nAdd to word list\nAdd to word list\nfeeling or showing unhappiness: \"It's no use - I can't do it,\" she said miserably. While the other kids played, we stared miserably out of the window.\nin a way that is very unpleasant and makes you unhappy: It's been miserably wet (= raining a lot) all week.\nSMART Vocabulary: related words and phrases\nFeeling sad and unhappy\na dog's life idiom\na long face idiom\nabjection\nangsty\nbe cut up idiom\nbe down in the mouth idiom\nbe in a funk idiom\ndistraught\ndistressed\ndog\ndoleful\nlovelorn\nlovesick\nlow-spirited\nlugubrious\nwistful\nwistfully\nwoe\nwoe is me idiom\nwoebegone\nSee more results »\nmiserably adverb\n(LOW VALUE)\nhaving little value, in a way that is disappointing: to fail miserably (= completely fail) miserably low wages\nSMART Vocabulary: related words and phrases\nCosting little or no money\naffordable housing\nbudget\ncatchpenny\nchargeless\ncheap\ncomp\ncompliment\ncostless\ndownmarket\neconomical\neconomically\nfor a song idiom\nmiserable\noff-peak\nrock bottom\nsmall change\nsupersaver\nultra-cheap\nworthlessly\nworthlessness\nSee more results »\nmiserably adverb\n(WITH LOW VALUE)\nAdd to word list\nAdd to word list\nin a way that brings completely bad results: Our leaders have failed miserably (= completely failed).\nmiserably adverb\n(UNHAPPILY)\nvery unhappily: She groaned miserably and trembled with anger."}