{"id":231262,"name":"mobocracy","type":"noun","us_sound":"mɑːˈbɑː.krə.si","us_link":"../audio/m/cdo0623usmobo2579.mp3","uk_sound":"mɒbˈɒk.rə.si","uk_link":"../audio/m/cdo0623ukmobo2579.mp3","content":"Add to word list\nAdd to word list\n[ U ] rule by a mob (= a large, angry crowd, especially one that could become violent): He contemptuously described their tactics as government by mobocracy. Instead of mobocracy, the party tried to offer another solution.\n[ C ] a mob that has power, or is in control : The mobocracy tries to force its will on the people. It was a mobocracy that scorned learning and terrorized the population.\nMore examplesFewer examplesWe need to avoid the dangerous extremes of both tyranny and mobocracy.Any group that tries to use the government to impose its own wishes on others is just a mobocracy.\nSMART Vocabulary: related words and phrases\nSystems of government\nabsolutism\nancien régime\nanti-apartheid\nanti-communism\nanti-federalist\ndemocratically\ndemocratization\ndemocratize\ndespotic\ndespotically\nkleptocratic\nmajority rule\nmartial law\nmatriarchal\nmatriarchy\npost-apartheid\npre-fascist\npure democracy\nregime\nreign\nSee more results »\nRelated word\nmobCompare\ndemocracy"}