{"id":234460,"name":"mouldering","type":"verb","us_sound":"ˈmoʊl.dɚ","us_link":"../audio/m/usmotli014.mp3","uk_sound":"ˈməʊl.dər","uk_link":"../audio/m/ukmotor014.mp3","content":"Add to word list\nAdd to word list\npresent participle of\nmoulder\nto decay slowly: I found these apples mouldering in the cupboard. Synonym\nrot\nto be left somewhere and not used or cared for: There's an old bike that's been mouldering away in the shed for years.\nSMART Vocabulary: related words and phrases\nDecaying and staying fresh\nbest-before date\nbiodegradable\nbiodegrade\ncompost\ndecay\ndecompose\nmoulder\nmouldy\nnonperishable\nnutrient cycling\nout of date\nperish\nputrid\nrack\nrotten\nsell-by date\nshrivel\nshrivelled\nsoft rot\nwithered\nSee more results »\nYou can also find related words, phrases, and synonyms in the topics:\nNeglecting and ignoring"}