{"id":234543,"name":"mounting","type":"adjective","us_sound":"ˈmaʊn.t̬ɪŋ","us_link":"../audio/m/mounting.mp3","uk_sound":"ˈmaʊn.tɪŋ","uk_link":"../audio/m/ukmotor027.mp3","content":"Add to word list\nAdd to word list\ngradually increasing: mounting anxiety/excitement mounting debts\nSMART Vocabulary: related words and phrases\nIncreasing and intensifying\naccretion\naccumulate\naccumulative\naccumulatively\nadd fuel to the fire idiom\nblaze\ncrank\ngo up\ngrowing\ngrowingly\nheighten\nhot up\ninflation\nmushroom\nratchet something up/down\nre-escalate\nre-escalation\nredouble\nresurge\nstake\nSee more results »\nAdd to word list\nAdd to word list\nincreasing or rising: There’s been mounting international criticism of the move."}