{"id":35929,"name":"blazon","type":"verb","us_sound":"ˈbleɪ.zən","us_link":"../audio/b/usblack020.mp3","uk_sound":"ˈbleɪ.zən","uk_link":"../audio/b/ukblank019.mp3","content":"Add to word list\nAdd to word list\n→\nemblazon\nSMART Vocabulary: related words and phrases\nApparent and obvious\n(from) under your nose idiom\napparent\nbe (as) plain as the nose on your face idiom\nbe (right) under your nose idiom\nbe etched somewhere idiom\nbe writ large idiom\nforegone conclusion\nglaring\nglaringly\nI need hardly do something idiom\nin plain sight idiom\nobtrude\npalpable\npalpably\nparallax\npatently\nperceivable\nsqueaky\nstand/stick out a mile idiom\nwritten all over someone's face idiom\nSee more results »"}