{"id":81296,"name":"briton","type":"noun","us_sound":"ˈbrɪt̬.ən","us_link":"../audio/b/usbriti002.mp3","uk_sound":"ˈbrɪt.ən","uk_link":"../audio/b/ukbrit_005.mp3","content":"Add to word list\nAdd to word list\na person from Britain: Six Britons are believed to have been involved in the accident. The book examines the life of the Ancient Britons before the coming of the Romans. Compare\nBrit informal\nBritisher US\nSMART Vocabulary: related words and phrases\nCountries, nationalities & continents: nationalities\nAfghan\nAlbanian\nAlgerian\nan\nAndorran\nGhanaian\nGibraltarian\nGreenlander\nGreenlandic\nGrenadian\nnon-Hispanic\nnon-Indian\nnon-Russian\nNorth American\nNorth Korean\nthe Vatican\nVenezuelan\nVietnamese\nVincentian\nVirgin Islands\nSee more results »\nAdd to word list\nAdd to word list\na person from Great Britain"}