{"id":194644,"name":"intending","type":"verb","us_sound":"ɪnˈtend","us_link":"../audio/i/intend.mp3","uk_sound":"ɪnˈtend","uk_link":"../audio/i/ukintem004.mp3","content":"Add to word list\nAdd to word list\npresent participle of\nintend\nB1 to have as a plan or purpose: [ + to infinitive ] We intend to go to Australia next year. Somehow I offended him, which wasn't what I'd intended. [ + obj + to infinitive ] I don't think she intended me to hear the remark. The course is intended for intermediate-level students. It was intended as a compliment, honestly!\nMore examplesFewer examplesThe president has announced she does not intend to stand for re-election.I made a promise to you and I intend to keep it.How do you intend to deal with this problem?I've heard that she intends to leave the company.I spent much more than I intended to.\nSMART Vocabulary: related words and phrases\nPlanning, expecting and arranging\naccidentally\naccidentally on purpose idiom\nadvertent\nadvisedly\naim at something\nbargain\nhave something up your sleeve idiom\nhorizon scanning\nhow are you fixed for something? idiom\nI might have known idiom\nI'll/we'll cross that bridge when I/we come/get to it idiom\npencil\nprovidently\nprovision\npurpose\npurposefully\npurposely\nput their heads together idiom\nsettle\nsleeve\nSee more results »"}