{"id":196249,"name":"intersperse","type":"verb","us_sound":"ˌɪn.t̬ɚˈspɝːs","us_link":"../audio/i/eus72550.mp3","uk_sound":"ˌɪn.təˈspɜːs","uk_link":"../audio/i/ukinter313.mp3","content":"Add to word list\nAdd to word list\nto mix one thing in with another in a way that is not regular: The documentary intersperses graphical animations with film clips of the actual event. Her handwritten notes were interspersed throughout the text.\nSMART Vocabulary: related words and phrases\nMixing and mixtures\namalgam\nbe neither one thing nor the other idiom\nblend\nblend in/blend into something\nblender\nblitz\ncrossed\ndecoction\nemulsion\nguaraná\nhomogeneous mixture\nmethylate\nmingle\nmosaic\nmush\nneither\nsaturated solution\nscramble\nsubstance\nsynthesis\nSee more results »\nYou can also find related words, phrases, and synonyms in the topics:\nInserting and forcing things into other things\nAdd to word list\nAdd to word list\nto put things of one type in different parts or places among other things: Framed pictures of her children were interspersed among the books in the bookcase."}