{"id":285745,"name":"preached","type":"verb","us_sound":"priːtʃ","us_link":"../audio/p/preach.mp3","uk_sound":"priːtʃ","uk_link":"../audio/p/ukpraye002.mp3","content":"Add to word list\nAdd to word list\npast simple and past participle of\npreach\npreach verb\n(IN CHURCH)\n[ I or T ] (especially of a priest or minister in a church) to give a religious speech: Father Martin preached to the assembled mourners. During the sermon, he preached about the need for forgiveness.\nSMART Vocabulary: related words and phrases\nMeditation, religious chanting & spiritual states\nasana\nchakra\nchant\nflotation\nincantation\nmantra\nmeditate\nmeditation\nmeditative\nmindful\nmindfully\nmindfulness\nnirvana\npreach\nsophrology\nTranscendental Meditation\nyoga\nyogic\npreach verb\n(PERSUADE)\n[ T ] to try to persuade other people to believe in a particular belief or follow a particular way of life: They preach the abolition of established systems but propose nothing to replace them.\nSMART Vocabulary: related words and phrases\nUrging & persuading\nambulance-chasing\nargumentation\nbe/go on at someone idiom\nblag\nblagger\nfob\ninduce\ninfluencer\njockey\njockey someone into something\njolly\nlean\nlean on someone/something\nlove bomb\nsucker\nunsellable\nurging\nwell argued\nwheedling\nwin someone over\nSee more results »\npreach verb\n(ADVISE)\n[ I ] disapproving to give unwanted advice, especially about moral matters, in a boring way: He's such a pain - he's always preaching about the virtues of working hard and getting up early. My mother's always preaching at/to me about keeping my room tidy.\nSMART Vocabulary: related words and phrases\nGiving advice\nadvice column\nadvice columnist\nadvisability\nadvisable\nadvise against doing something\nagony uncle\nbrain trust\nclinic\nconsultant\ncounselling\nguidance\nMonday-morning quarterback idiom\nPrivy Councillor\nrun over/through something\nshoe\nSpAd\nsteer\ntake someone's advice\ntalk some sense into sb idiom\nwaste\nSee more results »\nIdiom\npreach to the converted"}