{"id":292210,"name":"programmatic","type":"adjective","us_sound":"ˌproʊ.ɡrəˈmæt̬.ɪk","us_link":"../audio/p/cdo0318usprog3887.mp3","uk_sound":"ˌprəʊ.ɡrəˈmæt.ɪk","uk_link":"../audio/p/epd23132.mp3","content":"Add to word list\nAdd to word list\nhappening or done according to a plan or using a particular method: The company did not adopt a programmatic approach to change, preferring evolutionary development.\nusing or relating to computer programs: Web services enable programmatic access to a wide variety of data over the internet.\nSMART Vocabulary: related words and phrases\nPlans and arrangements\naccommodation\nappointed\narrangement\narranger\nbackstop\nblueprint\ncounter-strategy\ncounter-tactic\ndesign\ndone\nexit strategy\nmaster plan\nnon-programme\npackage deal\nparty line\nplan of action\nplanning\npolicy\npreparation\nwalk-in\nSee more results »\nYou can also find related words, phrases, and synonyms in the topics:\nComputer concepts\nComputer programming & software\nRelated word\nprogrammatically"}