{"id":105262,"name":"computable","type":"adjective","us_sound":"kəmˈpjuː.t̬ə.bəl","us_link":"../audio/c/cdo0623uscomp0633.mp3","uk_sound":"kəmˈpjuː.tə.bəl","uk_link":"../audio/c/cdo0623ukcomp0634.mp3","content":"Add to word list\nAdd to word list\nIf the answer to a mathematical problem is computable, you can calculate it by using a machine: The amount of heat produced by the process is easily computable. In theory, it is possible to express any computable function in one line of code.\nMore examplesFewer examplesUnfortunately, the answer to this question is not computable.He was trying to design a single machine that could be used to calculate any computable sequence.The precise amount that she owed was probably not computable.\nSMART Vocabulary: related words and phrases\nCalculations & calculating\nalgebraic\nalgebraically\nalgo\nalgorithmic\namount\ncalculate\nguesstimate\ninterpolate\nlinear equation\nmathematical\nmatrix\nmiscalculate\nmiscalculation\nmiscount\nmultigrid\nmultigroup\noperator\nroot\nsum\ntriangulation\nSee more results »\nRelated word\ncompute"}