{"id":135964,"name":"edelweiss","type":"noun","us_sound":"ˈeɪ.dəl.vaɪs","us_link":"../audio/e/cdo1121usedel1524.mp3","uk_sound":"ˈeɪ.dəl.vaɪs","uk_link":"../audio/e/cdo1121ukedel1454.mp3","content":"Add to word list\nAdd to word list\na mountain plant with small white flowers and grey-green leaves: It was an edelweiss, the symbolic flower of the German mountain troops. The alpine star, otherwise known as edelweiss, grows only at high altitude.\nMore examplesFewer examplesHe took three days to climb through the all the cows and daisies to get to the snow and blooming edelweiss of the upper slopes.On the way down we spotted Swiss flowers, such as the intense blue gentian and the iconic edelweiss.They wear distinctive caps with pins of the edelweiss flower on the side.The real lure of Mongolia is the chance to roam endless fields of wild grasses and edelweiss.\nSMART Vocabulary: related words and phrases\nFlowers & flowering plants\naconite\nadam-and-eve\naeonium\nAfrican daisy\nagapanthus\nelderflower\nelephant ear\nerythronium\neuphorbia\nevening primrose\nlords-and-ladies\nlotus\nlove-in-a-mist\nlupin\nmallow\nself-heal\nsenecio\nsensitive plant\nShasta daisy\nshepherd's purse\nSee more results »"}