{"id":146903,"name":"exceptionally","type":"adverb","us_sound":"ɪkˈsep.ʃən.əl.i","us_link":"../audio/e/exceptionally.mp3","uk_sound":"ɪkˈsep.ʃən.əl.i","uk_link":"../audio/e/ukexami027.mp3","content":"Add to word list\nAdd to word list\nin a way that is much greater than usual, especially in skill, intelligence, quality, etc.: an exceptionally fine portrait He is an exceptionally talented teacher. See\nexceptional\nMore examplesFewer examplesThe school is for exceptionally gifted musicians. The event has been exceptionally well attended.It's unclear whether he knew about the exceptionally high lead levels in the house.\nSMART Vocabulary: related words and phrases\nExtremely good\nadmirable\namazing\namazingly\nask for someone\naward-winning\ndivine\nfive-star\ngold-plated\ngourmet\ngreatness\nhave no parallel phrase\nhigh-class\npar excellence\nshining\nsock\nsplendid\nsplendidly\nstellar\nstupendously\nwonderfully\nSee more results »"}