{"id":149188,"name":"fabric","type":"noun","us_sound":"ˈfæb.rɪk","us_link":"../audio/f/fabric.mp3","uk_sound":"ˈfæb.rɪk","uk_link":"../audio/f/ukeyeto011.mp3","content":"fabric noun\n(CLOTH)\nAdd to word list\nAdd to word list\nC1 [ C or U ] cloth or material for making clothes, covering furniture, etc.: dress fabric seats upholstered in red fabric cotton fabrics\nMore examplesFewer examplesLinen is a coarse-grained fabric.The fibres are woven into fabric.This fabric is similar to wool, only cheaper.The designs are printed onto the fabric by hand.She designs her own fabrics using woodblocks and stencils to create patterns on the material.\nSMART Vocabulary: related words and phrases\nTextiles: general words\nbaize\nBargello\nbias\nbrocade\ncloth\ncutpiece\ndenier\nfibre\nmultifilament\nnap\npadding\npile\npill\nreweave\nsuiting\nswatch\ntextile\nthe weft\nwebbed\nyarn\nSee more results »\nfabric noun\n(STRUCTURE)\nthe fabric of something\nC2 the structure or parts of something: the fabric of society\nSee more\nfabric noun\n(CLOTH)\nAdd to word list\nAdd to word list\n[ C/U ] cloth or woven material, or a type of this material: [ U ] cotton fabric [ C ] Wash delicate fabrics by hand.\nfabric noun\n(STRUCTURE)\n[ U ] the structure of something; the parts of something that hold it together and make it what it is: Extreme social activism might rip apart the social fabric.\nAdd to word list\nAdd to word list\ncloth: Consumers are demanding lighter, easy-to-care-for fabrics. Competition from overseas fabric producers forced the company to shed 700 jobs."}