{"id":153271,"name":"fingertip","type":"noun","us_sound":"ˈfɪŋ.ɡɚ.tɪp","us_link":"../audio/f/usfinal012.mp3","uk_sound":"ˈfɪŋ.ɡə.tɪp","uk_link":"../audio/f/ukfinan024.mp3","content":"Add to word list\nAdd to word list\nthe end of a finger: Use your fingertips to gently flatten the pastry.\nSMART Vocabulary: related words and phrases\nThe hand\ncarpal\ncarpometacarpal\ncarpus\ncuticle\ndexterity\ndexterous\nfinger\nfingerprint\nknuckle\nleft-handed\nleft-hander\nlittle finger\nmetacarpus\nminimus\nopposable\npalm\npalmar\nphalangeal\npinkie\ntwo-handed\nSee more results »\nIdioms\nat your fingertips\nbe an artist, professional, etc. to your fingertips\nAdd to word list\nAdd to word list\nthe end of a finger Idiom\nat your fingertips"}