{"id":153579,"name":"first","type":"ordinal number","us_sound":"ˈfɝːst","us_link":"../audio/f/first.mp3","uk_sound":"ˈfɜːst","uk_link":"../audio/f/ukfirew008.mp3","content":"first ordinal number, determiner\n(BEFORE ALL OTHERS)\nAdd to word list\nAdd to word list\nA1 (a person or thing) coming before all others in order, time, amount, quality, or importance: This is my first visit to New York.the first time I fell in love with him the first time I saw him.first few I'm always nervous for the first few minutes of an exam.the first (of) Today is the first (of August). in the first place\nB2 in or at the beginning (of a series of events): The trousers shrank when I washed them, but they weren't really big enough in the first place.\nSee more in the first instance UK\nas the first attempt or effort: Enquiries about the post should be addressed in the first instance to the personnel manager.\nSee more of the first order\nto a very great degree or of an extremely good kind: It is a diplomatic scandal of the first order.\nSee more first thing\nat the earliest time in the day: He said he'd call back first thing tomorrow.\nSee more\nMore examplesFewer examplesYou roll/throw the dice and whoever gets the highest score goes first.Their first baby is due in January.When did you first encounter these difficulties?I was amazed to hear that Chris had won first prize.Yesterday the company announced its first ever fall in profits.\nSMART Vocabulary: related words and phrases\nFirst and firstly\nat first blush idiom\nat first idiom\nbegin\nblush\ndebut\nfirst come, first served idiom\nfrom the word go idiom\nfront end\nin the first/second place idiom\ninaugural\ninitial\ninitially\nplace\nprefatory\nprimary\nproto-\nprototypical\nstarter\nto begin with idiom\nword\nSee more results »\nfirst ordinal number, determiner\n(MUSIC)\n[ before noun ]\n&#160; music\n&#160; specialized in a group of musicians or singers, relating to the highest or higher instrument, voice, or part: She sings first soprano in the school choir. He is the best first trumpet player in the business. Unusually, the first altos have the tune. See also\nfirst violin\nSMART Vocabulary: related words and phrases\nMusicians\naccompanist\narranger\nartist\nbandleader\nbandmaster\ncrossover\ndrum major\ndrummer\nemcee\nfiddler\nmuso\nnon-musician\noboist\none-hit wonder\none-man band\nsight-reader\nsoloist\ntimpanist\ntrombonist\ntrumpeter\nSee more results »\nGrammar\nFirst, firstly or at first?First can be an adjective or an adverb and refers to the person or thing that comes before all others in order, time, amount, quality or importance: …\nIdioms\nbe in the first flush of\nfirst things first\nA1 before all others in order, time, amount, quality, or importance: come first Tom came first in the race. Who finished first? If you get home first, can you feed the cat?\nB1 for the first time: When did you first meet each other? The company was still very small when I first joined.\nA2 (also firstly) used at the beginning of a list of things you want to say or write: First, I want to thank my parents.first (of all) First (of all) (= before anything else), I'd like to ask you a few questions.first off First off (= before anything else), let me introduce myself.\nSMART Vocabulary: related words and phrases\nBefore, after and already\nafore\nafterwards\nalready\nante\nas it is idiom\nbefore\nheel\nimmediate\nin advance idiom\nin advance of something/someone idiom\nin the wake of something idiom\nnext\nposterior\nprevious\nprior\npriorly\nprologue\nquondam\nupstream\nwake\nSee more results »\nYou can also find related words, phrases, and synonyms in the topics:\nFirst and firstly\nGrammar\nFirst, firstly or at first?First can be an adjective or an adverb and refers to the person or thing that comes before all others in order, time, amount, quality or importance: …\nIdioms\nat first\ncome first\nfirst among equals\nfirst and foremost\nfirst and last\nfirst come, first served\nput someone/something first\nfirst noun\n(THING/PERSON)\nB1 [ S ] the first person or thing to do or be something, or the first person or thing mentioned: [ + to infinitive ] She was one of the first to arrive.the first to He is the first (= very willing) to admit that much of his success is due to his good looks. Tonight sees the first of three documentaries about cancer. from the (very) first\nfrom the beginning: I've opposed the proposal from the very first.\nSee more\nSMART Vocabulary: related words and phrases\nFirst and firstly\nat first blush idiom\nat first idiom\nbegin\nblush\ndebut\nfirst come, first served idiom\nfrom the word go idiom\nfront end\nin the first/second place idiom\ninaugural\ninitial\ninitially\nplace\nprefatory\nprimary\nproto-\nprototypical\nstarter\nto begin with idiom\nword\nSee more results »\nfirst noun\n(MUSIC)\n[ C ]\n&#160; music\n&#160; specialized In a group of musicians or singers, a first is a person who plays or sings the highest or a higher part: The second violins were seated on the right side of the stage, opposite the firsts. She's usually a first but today she's singing second.\nSMART Vocabulary: related words and phrases\nMusicians\naccompanist\narranger\nartist\nbandleader\nbandmaster\ncrossover\ndrum major\ndrummer\nemcee\nfiddler\nmuso\nnon-musician\noboist\none-hit wonder\none-man band\nsight-reader\nsoloist\ntimpanist\ntrombonist\ntrumpeter\nSee more results »\nfirst noun\n(NEVER BEFORE)\nC2 [ S ] something that has never happened or been done before: a first for This new surgical technique is a first for (= has never been done before in) the hospital.\nSMART Vocabulary: related words and phrases\nAlways & never\nagain\nall along idiom\nall-time\nalong\nalways\naye\never\nfail\nhell\nin all my (born) days idiom\nin/through all the years idiom\ninvariably\nkingdom\nmonth\non demand idiom\nperpetual\nperpetually\ntill/until kingdom come idiom\ntill/until the cows come home idiom\nwhenever\nSee more results »\nfirst noun\n(QUALIFICATION)\n[ C ] UK (also first-class degree) the best possible undergraduate university degree you can get in the UK and some other countries: first in She has a first in English from Newcastle University.\nSMART Vocabulary: related words and phrases\nMarks & results\n2:1\n2:2\nB, b\nC, c\nclass\ncontinuous assessment\nformatively\nGPA\ngrade boundary\ngrade-point average\nhonor student\npass\npass rate\npassing grade\npositive\npositivity\nscore\nstraight As\nstraight-A\nthird\nSee more results »\nfirst noun\n(VEHICLE)\n[ U ] (also first gear) (in a vehicle) the gear used when starting to drive forward or when driving up a steep hill\nSMART Vocabulary: related words and phrases\nThe engine & engine parts\nair filter\nalternator\nanti-roll\nantifreeze\nbiting point\nbrake\ncam\ncarburation\ncarburettor\nchoke\ndisc brake\ndistributor\ninternal combustion engine\nmanual transmission\nmuffler\nneutral\nsuspension\ntailpipe\ntappet\nwater-cooled\nSee more results »\nfirst noun\n(BASEBALL)\n[ C usually singular ] informal another word for\nfirst base : I caught the ball and calmly stepped on first. There were runners on first and third with nobody out.\nGrant Faint/Photolibrary/GettyImages\nSMART Vocabulary: related words and phrases\nBaseball & rounders\naround the horn idiom\nbag\nball\nballgame\nballplayer\nbase hit\nbases\nbeat\nbottom\nchopper\nflare\nfoul\nglove\nhomer\nsafe\nsecond base\nshag\nshortstop\nslider\nthe World Series\nSee more results »\nAdd to word list\nAdd to word list\n(a person or thing) coming before all others in order, time, amount, quality, or importance: Would you like to go first? [ C ] We leave on the first of August. At first (= In the beginning) I thought he was joking, but then I realized he meant it.\nFirst also means first base Idioms\nat first glance\nfirst (of all)\nfirst and foremost\nfirst come, first served\nfirst thing\nfirst things first\nin the first place\non a first-name basis"}