{"id":153825,"name":"fitful","type":"adjective","us_sound":"ˈfɪt.fəl","us_link":"../audio/f/fitful.mp3","uk_sound":"ˈfɪt.fəl","uk_link":"../audio/f/ukfistf004.mp3","content":"Add to word list\nAdd to word list\noften stopping and starting and not happening in a regular or continuous way: fitful breathing a fitful sleep\nSMART Vocabulary: related words and phrases\nFrequency & regularity - general words\n(as) regular as clockwork idiom\n-ly\nclockwork\nendemically\nerratic\nerratically\nfitfully\nirregular\nirregularly\nlike clockwork idiom\nmany\nmany a time idiom\non-off\nperiodic\nperiodically\nprevalence\nregularity\nreligiously\nunsynchronized\nwould\nSee more results »\nRelated word\nfitfully\nAdd to word list\nAdd to word list\ngoing off and on irregularly: Her breathing is fitful."}