{"id":343364,"name":"stateswoman","type":"noun","us_sound":"ˈsteɪtˌswʊm.ən","us_link":"../audio/s/uscld01914.mp3","uk_sound":"ˈsteɪtˌswʊm.ən","uk_link":"../audio/s/ukcld01914.mp3","content":"Add to word list\nAdd to word list\nan experienced female politician, especially one who is respected for making good judgments: an influential and admired elder stateswoman Compare\nstatesman\nSMART Vocabulary: related words and phrases\nPolitics - general words\nanti-capitalism\nanti-capitalist\nanti-communism\nanti-communist\nanti-fascism\ninterparty\ninterpellate\ninterpellation\ninterventionist\nlab\non message\nOrwellian\noverstep\nparliament\nparty politics\nstatesman\nstatesmanlike\nsubsidiarity\nsuper-conservative\nThatcherism\nSee more results »"}