{"id":344039,"name":"stepchild","type":"noun","us_sound":"ˈstep.tʃaɪld","us_link":"../audio/s/stepchild.mp3","uk_sound":"ˈstep.tʃaɪld","uk_link":"../audio/s/uksteep021.mp3","content":"Add to word list\nAdd to word list\nthe child of your husband or wife from a previous relationship\nSMART Vocabulary: related words and phrases\nFamily: non-blood relations\nauntie\nblended family\nbrother-in-law\nco-brother\nco-sister\ngoddaughter\ngodfather\ngodmother\ngodparent\ngodson\nnonbiologically\nsister-in-law\nson-in-law\nstep\nstepbrother\nstepmother\nstepmum\nstepparent\nstepsister\nstepson\nSee more results »\nAdd to word list\nAdd to word list\na child of a previous marriage of either a husband or a wife"}