{"id":345756,"name":"stormy","type":"adjective","us_sound":"ˈstɔːr.mi","us_link":"../audio/s/stormy.mp3","uk_sound":"ˈstɔː.mi","uk_link":"../audio/s/ukstore011.mp3","content":"stormy adjective\n(VIOLENT WEATHER)\nAdd to word list\nAdd to word list\nB2 with strong wind, heavy rain, and often thunder and lightning: stormy weather The sky was dark and stormy.\nThesaurus: synonyms, antonyms, and examples\nrainyrainyAnother rainy afternoon - you'll have to stay indoors and play, I'm afraid.wetWe're in for a wet morning, with showers lasting well into the afternoon.showeryIt will be showery overnight, but clear by morning.drizzlyIt was a grey, drizzly day.\nSee more results »\nSMART Vocabulary: related words and phrases\nPrecipitation: stormy weather\nangrily\nbolt\nbomb cyclone\nbombogenesis\ncyclogenesis\ncyclonic\nelectrical storm\nhurricane\nlightning\nsheet lightning\nstorm cloud\ntempestuously\nthunder\nthundersnow\nthunderstorm\nthundery\ntornadic\ntornado\nweather bomb\nwhirlwind\nSee more results »\nstormy adjective\n(EMOTIONAL REACTION)\nC1 involving a lot of strong argument and shouting: a stormy debate They had a passionate and often stormy relationship.\nSMART Vocabulary: related words and phrases\nAngry and displeased\nacridly\nacrimonious\nacrimoniously\naggrieved\namused\nexasperatedly\nfed up\nfed up to the back teeth idiom\nfit to be tied idiom\nfractiously\nmurder\nnot be a happy camper idiom\noutraged\npeeved\npiqued\nvolatility\nwarpath\nwound up\nwrathful\nwrathfully\nSee more results »\nstormy adjective\n(HAVING VIOLENT WEATHER)\nAdd to word list\nAdd to word list\nrelating to or affected by a storm: I remember one stormy afternoon when Marcelle and I were kept indoors by the weather. fig. The new president’s promise of dramatic change has already run into some stormy weather (= difficult problems) on Capitol Hill.\nstormy adjective\n(FULL OF STRONG FEELING)\nfull of difficulties or fights: He is best remembered for his stormy marriage to actress Bette Davis."}