{"id":354490,"name":"swatter","type":"noun","us_sound":"ˈswɑː.t̬ɚ","us_link":"../audio/s/cdo0319usswat1699.mp3","uk_sound":"ˈswɒt.ər","uk_link":"../audio/s/cdo0319ukswat1538.mp3","content":"Add to word list\nAdd to word list\nan object, usually flat with a handle, used for hitting insects: She complained that she needed to carry a fly swatter around all the time.\n/GettyImages\nMore examplesFewer examplesGrab the fly swatter. The rainy season has arrived, ushering in a plague of mosquitoes. Try to anticipate where the fly is going to jump when it first sees your swatter.The fly reacts within 100 milliseconds after it first spots the moving swatter. This is why the newspaper business is screwed — people buying swatters instead of newspapers."}