{"id":367050,"name":"tower","type":"noun","us_sound":"ˈtaʊ.ɚ","us_link":"../audio/t/tower.mp3","uk_sound":"taʊər","uk_link":"../audio/t/uktouch028.mp3","content":"Add to word list\nAdd to word list\nB1 a tall, narrow structure, often square or circular, that either forms part of a building or stands alone: the Eiffel tower There's a clock on the church tower. He works in an office tower in downtown San Francisco. Compare\nspire\nsteepleSee also\ntower block UK\nMartello tower\nsignal tower US\nwater tower\nwatchtower\nivory tower disapproving\ncooling tower\ncontrol tower\nclock tower\na tall, usually metal structure used for broadcasting: a radio/transmission tower Synonym\nmast (RADIO/TELEVISION)\nKypros/Moment/GettyImages\nMore examplesFewer examplesFrom the top of the tower, the outlook over the city was breathtaking.After their wedding the bells pealed out from the tower.The plan for a new office tower went ahead regardless of local opposition.Scaffolding has been erected around the tower and repair work will start next week.Don't go up the tower if you're afraid of heights.\nSMART Vocabulary: related words and phrases\nBuildings in general\n-bedroomed\nbeach hut\nbuilding\nbunkhouse\ncampanile\nfour-square\ngeodesic dome\nhalf-timbered\nheritage\nheritage-listed building\nnew-build\nnon-residential\nnon-structural\nNorman\nobservation tower\nresidential\nstructurally\nstructure\nturreted\nwarren\nSee more results »\nYou can also find related words, phrases, and synonyms in the topics:\nBroadcasting in general\nSee also\na tower of strength\nto be very tall or large, usually in a way that makes people feel respect: We turned the corner and there was the cathedral, towering in front of us. Synonym\nloom\nSMART Vocabulary: related words and phrases\nHigh, tall and deep\nabysmal\naltitude\nbottomless\ndeep\nectomorph\nelevated\neye level\nheight\nhigher\nlofty\novershadow\nrangy\nrear\nrear above/over something/someone\nstand\ntall\ntallish\ntallness\ntower above/over someone/something\ntowering\nSee more results »\nPhrasal verbs\ntower above/over someone/something\ntower above/over something\nAdd to word list\nAdd to word list\na tall, narrow structure that either forms part of a building or stands alone: a clock tower\nA tower is also a tall, usually metal structure used for broadcasting: a television tower\nto appear very tall or large, or to be much taller than something else: As we drove on, the Rocky Mountains towered before us. Although he’s only 14, David towers over his mother."}