{"id":372923,"name":"turbojet","type":"noun","us_sound":"ˈtɝː.boʊ.dʒet","us_link":"../audio/t/ustumul023.mp3","uk_sound":"ˈtɜː.bəʊ.dʒet","uk_link":"../audio/t/ukturbo004.mp3","content":"Add to word list\nAdd to word list\na turbine used as an engine, especially for an aircraft, that provides a forward force for movement from the gas it pushes out, or an aircraft driven by this type of engine\nSMART Vocabulary: related words and phrases\nAir travel: fixed-wing aircraft & helicopters\nair taxi\nairframe\nairliner\nairplane\namphibian\nautorotation\nbiplane\nchopper\ncopter\nhang-glider\nhelicopter\njumbo jet\nquadcopter\nrotor\nseaplane\nshuttle\nsuperjumbo\nsuperplane\nUAV\nultralight\nSee more results »"}