{"id":175331,"name":"hebdomadal","type":"adjective","us_sound":"hebˈdɑː.mə.dəl","us_link":"../audio/h/cdo0623ushebd1782.mp3","uk_sound":"hebˈdɒm.ə.dəl","uk_link":"../audio/h/cdo0623ukhebd1778.mp3","content":"Add to word list\nAdd to word list\nhappening or appearing once a week: The hebdomadal arts newspaper gives information on all of the concerts and fun cultural events happening around the city each week. A member of the Hebdomadal Council from 1953 to 1963, he became the university's chief spokesman on financial matters. Compare\nweekly\nMore examplesFewer examplesThe layout department held its hebdomadal meeting to decide which story should be featured on the cover of next week's issue. The payroll department announced that checks would be mailed out on a hebdomadal basis.\nSMART Vocabulary: related words and phrases\nRelating to regular periods of time\nafternoons\nannual\nannum\nbi-yearly\nbiannual\ncircadian rhythm\ndailiness\ndaily\nevenings\nfortnightly\nhourly\np.c.m.\np.w.\nper annum\nper calendar month\nquadrennial\nquadrennially\nquarterly\ntriennially\nweekly\nSee more results »"}