{"id":211225,"name":"lettering","type":"noun","us_sound":"ˈlet̬.ɚ.ɪŋ","us_link":"../audio/l/lettering.mp3","uk_sound":"ˈlet.ər.ɪŋ","uk_link":"../audio/l/ukles__021.mp3","content":"Add to word list\nAdd to word list\nwriting in a particular colour, style, etc.: a black box with gold lettering Synonym\ninscription\nSMART Vocabulary: related words and phrases\nPublishing: printing & word processing\n3-D printing\nbackspace\nbed\nboldface\nboldfaced\nbolding\nimpression\nimprint\nindent\nindentation\ninline\nprint run\nprint something out\nprinted\nprinting\nprinting press\nrubber stamp\ntypography\nunpublished\nxerography\nSee more results »\nAdd to word list\nAdd to word list\nwritten letters: The perfume comes in a black box with gold lettering.\nAdd to word list\nAdd to word list\nwriting in a particular colour, style, etc.: The company name appeared on the sign in gold lettering."}