{"id":121844,"name":"dependably","type":"adverb","us_sound":"dɪˈpen.də.bli","us_link":"../audio/d/usdenat018.mp3","uk_sound":"dɪˈpen.də.bli","uk_link":"../audio/d/ukdensi023.mp3","content":"Add to word list\nAdd to word list\nin a way that can be trusted: Our products are guaranteed to perform consistently and dependably for 25 years. Swiss chocolate is dependably delicious. See\ndependable\nMore examplesFewer examplesDemand is challenging exporters' ability to ship goods dependably.It's a state whose voters dependably turn out in large numbers whatever the weather.There is no guarantee of a week of uninterrupted sunshine, but it is quite dependably dry and pleasant.\nSMART Vocabulary: related words and phrases\nLoyal, faithful & dependable\na safe pair of hands idiom\nallegiance\naudaciously\nbe as good as your word idiom\nbe here for someone idiom\nbe there for someone idiom\nfaithfully\nfaithfulness\nfealty\nfidelity\nfiduciary\nhere\nreliable\nreliably\nself\nstalwart\nstalwartly\nultra-reliable\nundependable\nunto thine own self be true idiom\nSee more results »"}