{"id":129438,"name":"disposition","type":"noun","us_sound":"ˌdɪs.pəˈzɪʃ.ən","us_link":"../audio/d/disposition.mp3","uk_sound":"ˌdɪs.pəˈzɪʃ.ən","uk_link":"../audio/d/ukdispl012.mp3","content":"Add to word list\nAdd to word list\nC2 [ C usually singular ] the particular type of character that a person naturally has: She is of a nervous/cheerful/sunny disposition.\n[ S + to infinitive ] formal a natural tendency to do something, or to have or develop something: a disposition to deceive\nSMART Vocabulary: related words and phrases\nMind and personality\n-hearted\n-heartedly\n-heartedness\nalexithymia\nallism\nallistic\nalter ego\nambivert\nAsperger's syndrome\nhuman nature\nid\njib\nneurotypicality\nnoddle\nnoetic\nnoggin\nnon-identity\npsychoanalysis\npsychoanalytic\nsubconscious\nSee more results »\nYou can also find related words, phrases, and synonyms in the topics:\nHabitual behaviour\nAdd to word list\nAdd to word list\na person’s usual way of feeling or behaving; the tendency of a person to be happy, friendly, anxious, etc.: a cheerful disposition\nAdd to word list\nAdd to word list\n[ C or U ] the process of selling something or formally giving it to someone: We have no control over the disposition of the funds in that account. Not more than 30% of a Fund's gross income can be derived from gains from the sale or other disposition of securities held for less than three months.\n[ U ]\n&#160; LAW the way in which a formal process, such as a business deal or a matter dealt with in a court of law, is completed: This describes the principal issues raised in the review and states the Regulation Board's disposition of the proceeding. Payment of expenses incurred in advance of the final disposition of this lawsuit shall be conditional upon receipt of a detailed itemization."}