{"id":134917,"name":"dwarf","type":"noun","us_sound":"dwɔːrf","us_link":"../audio/d/dwarf.mp3","uk_sound":"dwɔːf","uk_link":"../audio/d/ukdusts011.mp3","content":"Add to word list\nAdd to word list\nin stories for children, a creature like a little man with magical powers: Snow White and the Seven Dwarfs\noften offensive a word, which is often offensive, for a person who has a medical condition that causes their height to be much shorter than average\nvery small: You can grow dwarf conifers in pots on the patio.\nThesaurus: synonyms, antonyms, and examples\nnot great in size, amount, etc.smallI live in a small town.littleShe's a good little girl.a littleI just want a little ice cream.a little (bit)I was a little bit upset that she ate the last piece of cake.tinyHis body was covered in tiny red spots.\nSee more results »\nSMART Vocabulary: related words and phrases\nSmall\nbaby\nbijou\nbite-sized\nclaustrophobically\ncompactly\nelfin\nmidget\nminiaturized\nmissy\nmodest\nmodestly\nno/not enough room to swing a cat idiom\non the large, small, etc. side idiom\nS, s\nsampler\nscaled-down\nscrubby\nshoe box\nshrunken\nwee\nSee more results »\nIf one thing dwarfs another, it makes it seem small by comparison: The new skyscraper will dwarf all those near it. This new crisis may well dwarf most that have gone before.\nSMART Vocabulary: related words and phrases\nHigh, tall and deep\nabysmal\naltitude\nbottomless\ndeep\nectomorph\nelevated\neye level\nheight\nhigher\nlofty\novershadow\nrangy\nrear\nrear above/over something/someone\nstand\ntall\ntallish\ntallness\ntower\ntower above/over someone/something\nSee more results »\ndwarf noun [C]\n(SMALL PERSON)\nAdd to word list\nAdd to word list\na person who is much smaller than the usual size, or (in stories for children) a creature like a little man, esp. one having magical powers\ndwarf noun [C]\n(STAR)\nearth science any of a group of stars that, compared to other stars, are not very large or bright, including the sun\ndwarf verb [T]\n(MAKE SMALL)\nto make something seem small by comparison: This year’s budget dwarfs all previous ones."}