{"id":124385,"name":"dyadic","type":"adjective","us_sound":"daɪˈæd.ɪk","us_link":"../audio/d/cdo0319usdyad0577.mp3","uk_sound":"daɪˈæd.ɪk","uk_link":"../audio/d/cdo0319ukdyad0501.mp3","content":"Add to word list\nAdd to word list\nformal consisting of two parts: a dyadic conception of government\nsocial science\n&#160; specialized relating to the interaction between two people: Even dyadic interactions can be very complex.\nSMART Vocabulary: related words and phrases\nNumbers: groups of things according to number\nbaker's dozen\nbrace\ncompanion\ncouple\ndozen\ndyad\ngross\nnull\npair\nquaternity\nscore\ntriad\ntrinity\ntrio\ntwosome\nYou can also find related words, phrases, and synonyms in the topics:\nBehaving, interacting and behaviour"}