{"id":167447,"name":"gnotobiotic","type":"adjective","us_sound":"ˌnoʊ.t̬oʊ.baɪˈɑː.t̬ɪk","us_link":"../audio/g/cdo0623usgnot1656.mp3","uk_sound":"ˌnəʊ.təʊ.baɪˈɒt.ɪk","uk_link":"../audio/g/cdo0623ukgnot1653.mp3","content":"Add to word list\nAdd to word list\nin which there are no unknown microorganisms (= very small organisms): Studies in gnotobiotic rats did not reveal any significant effects. These findings are consistent with the results of a previous study in gnotobiotic calves.\nMore examplesFewer examplesSimilar results were found when the experiments were carried out in gnotobiotic rats.He suggests that using gnotobiotic cows would be one way of reducing the risks of drinking unpasteurized milk.The microbiological flora of gnotobiotic animals is known.Water for animals in gnotobiotic isolators must be sterile.The mice were gnotobiotic rather than germ-free.\nSMART Vocabulary: related words and phrases\nBacteria, moulds, germs & viruses\nadenovirus\naerobe\namoeba\namoebic\nanti-HIV\nantimicrobial\nGram-negative\nGram-positive\nGram-variable\nhen of the woods\nhorn of plenty\nmicrobe\nMRSA\nprobiotic\nroot rot\nrotavirus\nRSV\nsaprozoic\nshigella\nstrep\nSee more results »"}