{"id":301475,"name":"rattly","type":"adjective","us_sound":"ˈræt̬.əl.i","us_link":"../audio/r/cdo0623usratt3271.mp3","uk_sound":"ˈræt.əl.i","uk_link":"../audio/r/cdo0623ukratt3295.mp3","content":"Add to word list\nAdd to word list\nlikely to rattle (= make a series of knocking sounds), or making a rattling noise: The bus was a rattly old double-decker, packed with local people. It's very different from the rattly lifts of our old apartment block.\nMore examplesFewer examplesWhen it started to rain, we all crouched under a huge, rattly plastic sheet.The town can be reached by a charming, rattly train from Palma. It's noisier and rattlier in the cab than in the passenger compartment. There are many ways to keep rattly old windows in good working order.\nSMART Vocabulary: related words and phrases\nSounds made by objects, movement or impact\nbang around\nbong\nburble\nchoo-choo\nchuff\nclick away\nclicker\nclinking\ncrunch\nplop\nresonance\nsplat\nsplutter\nsputter\nsqueak\ntintinnabulation\ntoot\nunsounded\nwhirr\nwhite noise\nSee more results »\nRelated word\nrattleCompare\nrattling"}