{"id":303962,"name":"rectangular","type":"adjective","us_sound":"rekˈtæŋ.ɡjə.lɚ","us_link":"../audio/r/rectangular.mp3","uk_sound":"rekˈtæŋ.ɡjə.lər","uk_link":"../audio/r/ukrecor022.mp3","content":"Add to word list\nAdd to word list\nB2 shaped like a rectangle\nExamples\nThe room is roughly rectangular.a rectangular area of grass\nSMART Vocabulary: related words and phrases\nGeometrical shapes\n-cornered\ncircularly\ncone\ncongruently\nconic\ncrescent\ncylindrically\novoid\npolyhedron\npolytope\nprism\npyramid\nquadrilateral\nrectangle\nrectangularly\nrhombus\nright triangle\nsemicircle\nthree-dimensional\ntrapezoid\nSee more results »\nAdd to word list\nAdd to word list\ngeometry having the shape of a rectangle: The painting consists of four rectangular blocks of color."}