{"id":306964,"name":"rekindled","type":"verb","us_sound":"ˌriːˈkɪn.dəl","us_link":"../audio/r/uscld01197.mp3","uk_sound":"ˌriːˈkɪn.dəl","uk_link":"../audio/r/ukcld01197.mp3","content":"Add to word list\nAdd to word list\npast simple and past participle of\nrekindle\nto make someone have a feeling that they had in the past: The holiday was a last chance to rekindle their love.\nSMART Vocabulary: related words and phrases\nRestoring and reviving\nbalsam\nbounce\nbounce back\nfacelift\nflip\nlick your wounds idiom\nmodernization\nmodernize\nmove with the times idiom\nrecrudescence\nregeneration\nregenerative\nrejuvenate\nrejuvenation\nresurgent\nresurrect\nresurrection\nresuscitation\nrevamp\nrevitalize\nSee more results »"}