{"id":311019,"name":"retry","type":"verb","us_sound":"ˌriːˈtraɪ","us_link":"../audio/r/cdo0318usretr4143.mp3","uk_sound":"ˌriːˈtraɪ","uk_link":"../audio/r/epd24131.mp3","content":"retry verb\n(LAW)\nAdd to word list\nAdd to word list\n[ T ] to try someone again in a court of law (= examine them to find out if they have committed a crime or not): The original jury could not come to a verdict in the case. The defendant was retried several months later and convicted of the crime.\nSMART Vocabulary: related words and phrases\nTaking legal action\nabatement order\nambulance-chasing\nappear for someone\nbring\nbring an action\ncomplainant\nindictment\ninstruct\nlegal action\nlitigant\nlitigate\nlitigation\nlitigious\npetitioner\nprosecution\nprosecutorial\nreindict\nreindictment\nspecimen charge\nsummons\nSee more results »\nYou can also find related words, phrases, and synonyms in the topics:\nRepeating an action\nretry verb\n(MAKE NEW ATTEMPT)\n[ I ] to try to do something again because you have not been successful the first time: Don't worry if you make a mistake; you can always retry until you get the result you want. If that doesn't work, retry with a different payment card.\nSMART Vocabulary: related words and phrases\nTrying and making an effort\nA game\nassault\nattempt\nattempted\nbackwards\nbid\ncommitment\ncrack\ngo for it idiom\ngo out of your way idiom\ngo the extra mile idiom\ngo to great lengths idiom\nGod helps those who help themselves idiom\nseek\nshoot\nstep on the gas idiom\nstick at something\nstick to something\nstick-to-itiveness\nstrain after/for effect idiom\nSee more results »\nYou can also find related words, phrases, and synonyms in the topics:\nStarting again"}